pytest_suite_timeout/__init__.py
pytest_suite_timeout/plugin.py
pytest_suite_timeout-0.0.2.dist-info/entry_points.txt
pytest_suite_timeout-0.0.2.dist-info/LICENSE.txt
pytest_suite_timeout-0.0.2.dist-info/WHEEL
pytest_suite_timeout-0.0.2.dist-info/METADATA
pytest_suite_timeout-0.0.2.dist-info/RECORD
