Metadata-Version: 2.1
Name: pytest-suite-timeout
Version: 0.0.2
Summary: A pytest plugin for ensuring max suite time
Author: Brian Okken
Requires-Python: >=3.7
Classifier: License :: OSI Approved :: MIT License
Classifier: Framework :: Pytest
Requires-Dist: pytest>=7.0.0
Project-URL: Home, https://github.com/okken/pytest-suite-timeout
